03_barrelshifter/barrelshifter.v
module barrelshifter (
    input wire [31:0] datain,
    input wire [4:0] shiftamt, // shift amount
    input wire [2:0] operation, 
    /* operation type:
        0 - rotate right
        1 - rotate left
        2 - logical left shift
        3 - logical right shift
        rest - out = 0
    */
    output wire [31:0] dataout
);

    wire [63:0] temp1;

    assign temp1 =      {datain,datain} << shiftamt;
    assign dataout =    (operation == 3'd0) ? {datain,datain} >> shiftamt : 
                        (operation == 3'd1) ? temp1[63:32] :
                        (operation == 3'd2) ? datain << shiftamt:
                        (operation == 3'd3) ? datain >> shiftamt:
                        32'd0;
    
endmodule

03_barrelshifter/barrelshifter_tb.v
module barrelshifter_tb;

    reg  [31:0] datain;
    reg  [4:0]  shiftamt;
    reg  [2:0]  operation;
    wire [31:0] dataout;

    integer pass_count, fail_count, test_num;

    barrelshifter dut (
        .datain(datain),
        .shiftamt(shiftamt),
        .operation(operation),
        .dataout(dataout)
    );

    task apply_and_check;
        input [2:0]  op;
        input [31:0] din;
        input [4:0]  samt;
        input [31:0] expected;
        begin
            operation = op;
            datain    = din;
            shiftamt  = samt;
            #10;
            test_num = test_num + 1;
            if (dataout === expected) begin
                $display("PASS [%0d] op=%0d  data=0x%h  shift=%2d  out=0x%h",
                          test_num, op, din, samt, dataout);
                pass_count = pass_count + 1;
            end else begin
                $display("FAIL [%0d] op=%0d  data=0x%h  shift=%2d  expected=0x%h  got=0x%h",
                          test_num, op, din, samt, expected, dataout);
                fail_count = fail_count + 1;
            end
        end
    endtask

    initial begin
        $dumpfile("barrelshifter.vcd");
        $dumpvars(0, barrelshifter_tb);

        pass_count = 0;
        fail_count = 0;
        test_num   = 0;

        // -------------------------------------------------------
        // Rotate Right (op=0)
        // -------------------------------------------------------
        $display("\n--- Rotate Right (op=0) ---");
        apply_and_check(3'd0, 32'hABCD1234, 5'd0,  32'hABCD1234); // no shift
        apply_and_check(3'd0, 32'hABCD1234, 5'd4,  32'h4ABCD123);
        apply_and_check(3'd0, 32'hABCD1234, 5'd16, 32'h1234ABCD);
        apply_and_check(3'd0, 32'hABCD1234, 5'd31, 32'h579A2469); // same as ROL 1
        apply_and_check(3'd0, 32'h00000001, 5'd1,  32'h80000000); // LSB wraps to MSB
        apply_and_check(3'd0, 32'h80000000, 5'd1,  32'h40000000);
        apply_and_check(3'd0, 32'hFFFFFFFF, 5'd16, 32'hFFFFFFFF);
        apply_and_check(3'd0, 32'h00000000, 5'd15, 32'h00000000);

        // -------------------------------------------------------
        // Rotate Left (op=1)
        // -------------------------------------------------------
        $display("\n--- Rotate Left (op=1) ---");
        apply_and_check(3'd1, 32'hABCD1234, 5'd0,  32'hABCD1234); // no shift
        apply_and_check(3'd1, 32'hABCD1234, 5'd4,  32'hBCD1234A);
        apply_and_check(3'd1, 32'hABCD1234, 5'd16, 32'h1234ABCD);
        apply_and_check(3'd1, 32'hABCD1234, 5'd31, 32'h55E6891A); // same as ROR 1
        apply_and_check(3'd1, 32'h80000000, 5'd1,  32'h00000001); // MSB wraps to LSB
        apply_and_check(3'd1, 32'h00000001, 5'd1,  32'h00000002);
        apply_and_check(3'd1, 32'hFFFFFFFF, 5'd16, 32'hFFFFFFFF);
        apply_and_check(3'd1, 32'h00000000, 5'd15, 32'h00000000);

        // -------------------------------------------------------
        // Logical Left Shift (op=2)
        // -------------------------------------------------------
        $display("\n--- Logical Left Shift (op=2) ---");
        apply_and_check(3'd2, 32'hABCD1234, 5'd0,  32'hABCD1234); // no shift
        apply_and_check(3'd2, 32'hABCD1234, 5'd4,  32'hBCD12340);
        apply_and_check(3'd2, 32'hABCD1234, 5'd16, 32'h12340000);
        apply_and_check(3'd2, 32'hABCD1234, 5'd31, 32'h00000000); // bit[0]=0, all lost
        apply_and_check(3'd2, 32'h00000001, 5'd1,  32'h00000002);
        apply_and_check(3'd2, 32'hFFFFFFFF, 5'd1,  32'hFFFFFFFE);
        apply_and_check(3'd2, 32'h80000000, 5'd1,  32'h00000000); // MSB shifts out
        apply_and_check(3'd2, 32'h00000000, 5'd16, 32'h00000000);

        // -------------------------------------------------------
        // Logical Right Shift (op=3)
        // -------------------------------------------------------
        $display("\n--- Logical Right Shift (op=3) ---");
        apply_and_check(3'd3, 32'hABCD1234, 5'd0,  32'hABCD1234); // no shift
        apply_and_check(3'd3, 32'hABCD1234, 5'd4,  32'h0ABCD123);
        apply_and_check(3'd3, 32'hABCD1234, 5'd16, 32'h0000ABCD);
        apply_and_check(3'd3, 32'hABCD1234, 5'd31, 32'h00000001); // only MSB remains
        apply_and_check(3'd3, 32'h80000000, 5'd1,  32'h40000000); // MSB becomes 0 (logical)
        apply_and_check(3'd3, 32'hFFFFFFFF, 5'd1,  32'h7FFFFFFF);
        apply_and_check(3'd3, 32'h00000001, 5'd1,  32'h00000000);
        apply_and_check(3'd3, 32'h00000000, 5'd16, 32'h00000000);

        // -------------------------------------------------------
        // Default / undefined operations (op=5,6,7) → expect 0
        // -------------------------------------------------------
        $display("\n--- Default: undefined ops (op=5,6,7) ---");
        apply_and_check(3'd5, 32'hABCD1234, 5'd4,  32'h00000000);
        apply_and_check(3'd6, 32'hABCD1234, 5'd4,  32'h00000000);
        apply_and_check(3'd7, 32'hFFFFFFFF, 5'd0,  32'h00000000);

        $display("\n=== Results: %0d passed, %0d failed out of %0d tests ===",
                  pass_count, fail_count, test_num);
        $finish;
    end

endmodule

03_barrelshifter/barrelshifter.vcd
$date
	Sun May 17 20:41:02 2026
$end
$version
	Icarus Verilog
$end
$timescale
	1s
$end
$scope module barrelshifter_tb $end
$var wire 32 ! dataout [31:0] $end
$var reg 32 " datain [31:0] $end
$var reg 3 # operation [2:0] $end
$var reg 5 $ shiftamt [4:0] $end
$var integer 32 % fail_count [31:0] $end
$var integer 32 & pass_count [31:0] $end
$var integer 32 ' test_num [31:0] $end
$scope module dut $end
$var wire 32 ( datain [31:0] $end
$var wire 3 ) operation [2:0] $end
$var wire 5 * shiftamt [4:0] $end
$var wire 64 + temp1 [63:0] $end
$var wire 32 , dataout [31:0] $end
$upscope $end
$scope task apply_and_check $end
$var reg 32 - din [31:0] $end
$var reg 32 . expected [31:0] $end
$var reg 3 / op [2:0] $end
$var reg 5 0 samt [4:0] $end
$upscope $end
$upscope $end
$enddefinitions $end
#0
$dumpvars
b0 0
b0 /
b10101011110011010001001000110100 .
b10101011110011010001001000110100 -
b10101011110011010001001000110100 ,
b1010101111001101000100100011010010101011110011010001001000110100 +
b0 *
b0 )
b10101011110011010001001000110100 (
b0 '
b0 &
b0 %
b0 $
b0 #
b10101011110011010001001000110100 "
b10101011110011010001001000110100 !
$end
#10
b1001010101111001101000100100011 !
b1001010101111001101000100100011 ,
b1011110011010001001000110100101010111100110100010010001101000000 +
b100 $
b100 *
b1001010101111001101000100100011 .
b100 0
b1 &
b1 '
#20
b10010001101001010101111001101 !
b10010001101001010101111001101 ,
b1001000110100101010111100110100010010001101000000000000000000 +
b10000 $
b10000 *
b10010001101001010101111001101 .
b10000 0
b10 &
b10 '
#30
b1010111100110100010010001101001 !
b1010111100110100010010001101001 ,
b101010111100110100010010001101000000000000000000000000000000000 +
b11111 $
b11111 *
b1010111100110100010010001101001 .
b11111 0
b11 &
b11 '
#40
b10000000000000000000000000000000 !
b10000000000000000000000000000000 ,
b1 $
b1 *
b1000000000000000000000000000000010 +
b1 "
b1 (
b10000000000000000000000000000000 .
b1 0
b1 -
b100 &
b100 '
#50
b1000000000000000000000000000000 !
b1000000000000000000000000000000 ,
b100000000000000000000000000000000 +
b10000000000000000000000000000000 "
b10000000000000000000000000000000 (
b1000000000000000000000000000000 .
b10000000000000000000000000000000 -
b101 &
b101 '
#60
b11111111111111111111111111111111 !
b11111111111111111111111111111111 ,
b10000 $
b10000 *
b1111111111111111111111111111111111111111111111110000000000000000 +
b11111111111111111111111111111111 "
b11111111111111111111111111111111 (
b11111111111111111111111111111111 .
b10000 0
b11111111111111111111111111111111 -
b110 &
b110 '
#70
b0 !
b0 ,
b1111 $
b1111 *
b0 +
b0 "
b0 (
b0 .
b1111 0
b0 -
b111 &
b111 '
#80
b10101011110011010001001000110100 !
b10101011110011010001001000110100 ,
b0 $
b0 *
b1010101111001101000100100011010010101011110011010001001000110100 +
b10101011110011010001001000110100 "
b10101011110011010001001000110100 (
b1 #
b1 )
b10101011110011010001001000110100 .
b0 0
b10101011110011010001001000110100 -
b1 /
b1000 &
b1000 '
#90
b10111100110100010010001101001010 !
b10111100110100010010001101001010 ,
b1011110011010001001000110100101010111100110100010010001101000000 +
b100 $
b100 *
b10111100110100010010001101001010 .
b100 0
b1001 &
b1001 '
#100
b10010001101001010101111001101 !
b10010001101001010101111001101 ,
b1001000110100101010111100110100010010001101000000000000000000 +
b10000 $
b10000 *
b10010001101001010101111001101 .
b10000 0
b1010 &
b1010 '
#110
b1010101111001101000100100011010 !
b1010101111001101000100100011010 ,
b101010111100110100010010001101000000000000000000000000000000000 +
b11111 $
b11111 *
b1010101111001101000100100011010 .
b11111 0
b1011 &
b1011 '
#120
b1 !
b1 ,
b1 $
b1 *
b100000000000000000000000000000000 +
b10000000000000000000000000000000 "
b10000000000000000000000000000000 (
b1 .
b1 0
b10000000000000000000000000000000 -
b1100 &
b1100 '
#130
b10 !
b10 ,
b1000000000000000000000000000000010 +
b1 "
b1 (
b10 .
b1 -
b1101 &
b1101 '
#140
b11111111111111111111111111111111 !
b11111111111111111111111111111111 ,
b10000 $
b10000 *
b1111111111111111111111111111111111111111111111110000000000000000 +
b11111111111111111111111111111111 "
b11111111111111111111111111111111 (
b11111111111111111111111111111111 .
b10000 0
b11111111111111111111111111111111 -
b1110 &
b1110 '
#150
b0 !
b0 ,
b1111 $
b1111 *
b0 +
b0 "
b0 (
b0 .
b1111 0
b0 -
b1111 &
b1111 '
#160
b10101011110011010001001000110100 !
b10101011110011010001001000110100 ,
b0 $
b0 *
b1010101111001101000100100011010010101011110011010001001000110100 +
b10101011110011010001001000110100 "
b10101011110011010001001000110100 (
b10 #
b10 )
b10101011110011010001001000110100 .
b0 0
b10101011110011010001001000110100 -
b10 /
b10000 &
b10000 '
#170
b10111100110100010010001101000000 !
b10111100110100010010001101000000 ,
b1011110011010001001000110100101010111100110100010010001101000000 +
b100 $
b100 *
b10111100110100010010001101000000 .
b100 0
b10001 &
b10001 '
#180
b10010001101000000000000000000 !
b10010001101000000000000000000 ,
b1001000110100101010111100110100010010001101000000000000000000 +
b10000 $
b10000 *
b10010001101000000000000000000 .
b10000 0
b10010 &
b10010 '
#190
b0 !
b0 ,
b101010111100110100010010001101000000000000000000000000000000000 +
b11111 $
b11111 *
b0 .
b11111 0
b10011 &
b10011 '
#200
b10 !
b10 ,
b1 $
b1 *
b1000000000000000000000000000000010 +
b1 "
b1 (
b10 .
b1 0
b1 -
b10100 &
b10100 '
#210
b11111111111111111111111111111110 !
b11111111111111111111111111111110 ,
b1111111111111111111111111111111111111111111111111111111111111110 +
b11111111111111111111111111111111 "
b11111111111111111111111111111111 (
b11111111111111111111111111111110 .
b11111111111111111111111111111111 -
b10101 &
b10101 '
#220
b0 !
b0 ,
b100000000000000000000000000000000 +
b10000000000000000000000000000000 "
b10000000000000000000000000000000 (
b0 .
b10000000000000000000000000000000 -
b10110 &
b10110 '
#230
b10000 $
b10000 *
b0 +
b0 "
b0 (
b10000 0
b0 -
b10111 &
b10111 '
#240
b10101011110011010001001000110100 !
b10101011110011010001001000110100 ,
b0 $
b0 *
b1010101111001101000100100011010010101011110011010001001000110100 +
b10101011110011010001001000110100 "
b10101011110011010001001000110100 (
b11 #
b11 )
b10101011110011010001001000110100 .
b0 0
b10101011110011010001001000110100 -
b11 /
b11000 &
b11000 '
#250
b1010101111001101000100100011 !
b1010101111001101000100100011 ,
b1011110011010001001000110100101010111100110100010010001101000000 +
b100 $
b100 *
b1010101111001101000100100011 .
b100 0
b11001 &
b11001 '
#260
b1010101111001101 !
b1010101111001101 ,
b1001000110100101010111100110100010010001101000000000000000000 +
b10000 $
b10000 *
b1010101111001101 .
b10000 0
b11010 &
b11010 '
#270
b1 !
b1 ,
b101010111100110100010010001101000000000000000000000000000000000 +
b11111 $
b11111 *
b1 .
b11111 0
b11011 &
b11011 '
#280
b1000000000000000000000000000000 !
b1000000000000000000000000000000 ,
b1 $
b1 *
b100000000000000000000000000000000 +
b10000000000000000000000000000000 "
b10000000000000000000000000000000 (
b1000000000000000000000000000000 .
b1 0
b10000000000000000000000000000000 -
b11100 &
b11100 '
#290
b1111111111111111111111111111111 !
b1111111111111111111111111111111 ,
b1111111111111111111111111111111111111111111111111111111111111110 +
b11111111111111111111111111111111 "
b11111111111111111111111111111111 (
b1111111111111111111111111111111 .
b11111111111111111111111111111111 -
b11101 &
b11101 '
#300
b0 !
b0 ,
b1000000000000000000000000000000010 +
b1 "
b1 (
b0 .
b1 -
b11110 &
b11110 '
#310
b10000 $
b10000 *
b0 +
b0 "
b0 (
b10000 0
b0 -
b11111 &
b11111 '
#320
b100 $
b100 *
b1011110011010001001000110100101010111100110100010010001101000000 +
b10101011110011010001001000110100 "
b10101011110011010001001000110100 (
b101 #
b101 )
b100 0
b10101011110011010001001000110100 -
b101 /
b100000 &
b100000 '
#330
b110 #
b110 )
b110 /
b100001 &
b100001 '
#340
b0 $
b0 *
b1111111111111111111111111111111111111111111111111111111111111111 +
b11111111111111111111111111111111 "
b11111111111111111111111111111111 (
b111 #
b111 )
b0 0
b11111111111111111111111111111111 -
b111 /
b100010 &
b100010 '
#350
b100011 &
b100011 '
