02_roundrobinarbiter/rrarb.v
module rrarb (
    input wire [3:0] req,
    input wire clk,
    input wire rst,
    output wire [1:0] gnt
);
    reg [1:0] ptr;
    reg [1:0] gntreg;
    wire [7:0] reqreq;
    wire [3:0] window;
    wire [1:0] win;

    assign reqreq = {req,req}; // [r3,r2,r1,r0,r3,r2,r1,r0]
    assign gnt = gntreg;

    assign window = reqreq[ptr +: 4]; // window = reqreq[ptr+3:ptr]
    assign win = window[0] ? ptr :
                 window[1] ? ptr+1 :
                 window[2] ? ptr+2 :
                 window[3] ? ptr+3 :
                 0;

    always @(posedge clk or negedge rst) begin
        if (!rst) gntreg <= 2'b0;
        else if (req != 4'b0) gntreg <= win;
    end

    always @(posedge clk or negedge rst) begin
        if (!rst) ptr <= 2'b0;
        else if (req != 4'b0) ptr <= (win + 1);
    end

endmodule

02_roundrobinarbiter/rrarb_tb.v
`timescale 1ns/1ps

module rrarb_tb;
    reg [3:0] req;
    reg clk;
    reg rst;
    wire [1:0] gnt;

    rrarb dut(
        .req    (req),
        .clk    (clk),
        .rst    (rst),
        .gnt    (gnt)
    );

    initial clk = 0;
    initial rst = 1;
    always #5 clk = ~clk;

    initial begin
        $dumpfile("rrarb_tb.vcd");
        $dumpvars(0, rrarb_tb);
        #1000;
        $finish;
    end

    // TEST
    initial begin
        #5 rst = 0;
        #5 rst = 1;
        #14 req = 4'b1110;
    end
endmodule

02_roundrobinarbiter/rrarb_tb.vcd
$date
	Sun May 17 00:36:43 2026
$end
$version
	Icarus Verilog
$end
$timescale
	1ps
$end
$scope module rrarb_tb $end
$var wire 2 ! gnt [1:0] $end
$var reg 1 " clk $end
$var reg 4 # req [3:0] $end
$var reg 1 $ rst $end
$scope module dut $end
$var wire 1 " clk $end
$var wire 2 % gnt [1:0] $end
$var wire 4 & req [3:0] $end
$var wire 1 $ rst $end
$var wire 4 ' window [3:0] $end
$var wire 2 ( win [1:0] $end
$var wire 8 ) reqreq [7:0] $end
$var reg 2 * gntreg [1:0] $end
$var reg 2 + ptr [1:0] $end
$upscope $end
$upscope $end
$enddefinitions $end
#0
$dumpvars
bx +
bx *
bx )
bx (
bx '
bx &
bx %
1$
bx #
0"
bx !
$end
#5000
b0 !
b0 %
b0 *
b0 +
0$
1"
#10000
1$
0"
#15000
1"
#20000
0"
#24000
b1 (
b1110 '
b11101110 )
b1110 #
b1110 &
#25000
b10 (
b1 !
b1 %
b1 *
b1011 '
b10 +
1"
#30000
0"
#35000
b11 (
b1101 '
b11 +
b10 !
b10 %
b10 *
1"
#40000
0"
#45000
b1 (
b11 !
b11 %
b11 *
b1110 '
b0 +
1"
#50000
0"
#55000
b10 (
b1011 '
b10 +
b1 !
b1 %
b1 *
1"
#60000
0"
#65000
b11 (
b10 !
b10 %
b10 *
b1101 '
b11 +
1"
#70000
0"
#75000
b1 (
b1110 '
b0 +
b11 !
b11 %
b11 *
1"
#80000
0"
#85000
b10 (
b1 !
b1 %
b1 *
b1011 '
b10 +
1"
#90000
0"
#95000
b11 (
b1101 '
b11 +
b10 !
b10 %
b10 *
1"
#100000
0"
#105000
b1 (
b11 !
b11 %
b11 *
b1110 '
b0 +
1"
#110000
0"
#115000
b10 (
b1011 '
b10 +
b1 !
b1 %
b1 *
1"
#120000
0"
#125000
b11 (
b10 !
b10 %
b10 *
b1101 '
b11 +
1"
#130000
0"
#135000
b1 (
b1110 '
b0 +
b11 !
b11 %
b11 *
1"
#140000
0"
#145000
b10 (
b1 !
b1 %
b1 *
b1011 '
b10 +
1"
#150000
0"
#155000
b11 (
b1101 '
b11 +
b10 !
b10 %
b10 *
1"
#160000
0"
#165000
b1 (
b11 !
b11 %
b11 *
b1110 '
b0 +
1"
#170000
0"
#175000
b10 (
b1011 '
b10 +
b1 !
b1 %
b1 *
1"
#180000
0"
#185000
b11 (
b10 !
b10 %
b10 *
b1101 '
b11 +
1"
#190000
0"
#195000
b1 (
b1110 '
b0 +
b11 !
b11 %
b11 *
1"
#200000
0"
#205000
b10 (
b1 !
b1 %
b1 *
b1011 '
b10 +
1"
#210000
0"
#215000
b11 (
b1101 '
b11 +
b10 !
b10 %
b10 *
1"
#220000
0"
#225000
b1 (
b11 !
b11 %
b11 *
b1110 '
b0 +
1"
#230000
0"
#235000
b10 (
b1011 '
b10 +
b1 !
b1 %
b1 *
1"
#240000
0"
#245000
b11 (
b10 !
b10 %
b10 *
b1101 '
b11 +
1"
#250000
0"
#255000
b1 (
b1110 '
b0 +
b11 !
b11 %
b11 *
1"
#260000
0"
#265000
b10 (
b1 !
b1 %
b1 *
b1011 '
b10 +
1"
#270000
0"
#275000
b11 (
b1101 '
b11 +
b10 !
b10 %
b10 *
1"
#280000
0"
#285000
b1 (
b11 !
b11 %
b11 *
b1110 '
b0 +
1"
#290000
0"
#295000
b10 (
b1011 '
b10 +
b1 !
b1 %
b1 *
1"
#300000
0"
#305000
b11 (
b10 !
b10 %
b10 *
b1101 '
b11 +
1"
#310000
0"
#315000
b1 (
b1110 '
b0 +
b11 !
b11 %
b11 *
1"
#320000
0"
#325000
b10 (
b1 !
b1 %
b1 *
b1011 '
b10 +
1"
#330000
0"
#335000
b11 (
b1101 '
b11 +
b10 !
b10 %
b10 *
1"
#340000
0"
#345000
b1 (
b11 !
b11 %
b11 *
b1110 '
b0 +
1"
#350000
0"
#355000
b10 (
b1011 '
b10 +
b1 !
b1 %
b1 *
1"
#360000
0"
#365000
b11 (
b10 !
b10 %
b10 *
b1101 '
b11 +
1"
#370000
0"
#375000
b1 (
b1110 '
b0 +
b11 !
b11 %
b11 *
1"
#380000
0"
#385000
b10 (
b1 !
b1 %
b1 *
b1011 '
b10 +
1"
#390000
0"
#395000
b11 (
b1101 '
b11 +
b10 !
b10 %
b10 *
1"
#400000
0"
#405000
b1 (
b11 !
b11 %
b11 *
b1110 '
b0 +
1"
#410000
0"
#415000
b10 (
b1011 '
b10 +
b1 !
b1 %
b1 *
1"
#420000
0"
#425000
b11 (
b10 !
b10 %
b10 *
b1101 '
b11 +
1"
#430000
0"
#435000
b1 (
b1110 '
b0 +
b11 !
b11 %
b11 *
1"
#440000
0"
#445000
b10 (
b1 !
b1 %
b1 *
b1011 '
b10 +
1"
#450000
0"
#455000
b11 (
b1101 '
b11 +
b10 !
b10 %
b10 *
1"
#460000
0"
#465000
b1 (
b11 !
b11 %
b11 *
b1110 '
b0 +
1"
#470000
0"
#475000
b10 (
b1011 '
b10 +
b1 !
b1 %
b1 *
1"
#480000
0"
#485000
b11 (
b10 !
b10 %
b10 *
b1101 '
b11 +
1"
#490000
0"
#495000
b1 (
b1110 '
b0 +
b11 !
b11 %
b11 *
1"
#500000
0"
#505000
b10 (
b1 !
b1 %
b1 *
b1011 '
b10 +
1"
#510000
0"
#515000
b11 (
b1101 '
b11 +
b10 !
b10 %
b10 *
1"
#520000
0"
#525000
b1 (
b11 !
b11 %
b11 *
b1110 '
b0 +
1"
#530000
0"
#535000
b10 (
b1011 '
b10 +
b1 !
b1 %
b1 *
1"
#540000
0"
#545000
b11 (
b10 !
b10 %
b10 *
b1101 '
b11 +
1"
#550000
0"
#555000
b1 (
b1110 '
b0 +
b11 !
b11 %
b11 *
1"
#560000
0"
#565000
b10 (
b1 !
b1 %
b1 *
b1011 '
b10 +
1"
#570000
0"
#575000
b11 (
b1101 '
b11 +
b10 !
b10 %
b10 *
1"
#580000
0"
#585000
b1 (
b11 !
b11 %
b11 *
b1110 '
b0 +
1"
#590000
0"
#595000
b10 (
b1011 '
b10 +
b1 !
b1 %
b1 *
1"
#600000
0"
#605000
b11 (
b10 !
b10 %
b10 *
b1101 '
b11 +
1"
#610000
0"
#615000
b1 (
b1110 '
b0 +
b11 !
b11 %
b11 *
1"
#620000
0"
#625000
b10 (
b1 !
b1 %
b1 *
b1011 '
b10 +
1"
#630000
0"
#635000
b11 (
b1101 '
b11 +
b10 !
b10 %
b10 *
1"
#640000
0"
#645000
b1 (
b11 !
b11 %
b11 *
b1110 '
b0 +
1"
#650000
0"
#655000
b10 (
b1011 '
b10 +
b1 !
b1 %
b1 *
1"
#660000
0"
#665000
b11 (
b10 !
b10 %
b10 *
b1101 '
b11 +
1"
#670000
0"
#675000
b1 (
b1110 '
b0 +
b11 !
b11 %
b11 *
1"
#680000
0"
#685000
b10 (
b1 !
b1 %
b1 *
b1011 '
b10 +
1"
#690000
0"
#695000
b11 (
b1101 '
b11 +
b10 !
b10 %
b10 *
1"
#700000
0"
#705000
b1 (
b11 !
b11 %
b11 *
b1110 '
b0 +
1"
#710000
0"
#715000
b10 (
b1011 '
b10 +
b1 !
b1 %
b1 *
1"
#720000
0"
#725000
b11 (
b10 !
b10 %
b10 *
b1101 '
b11 +
1"
#730000
0"
#735000
b1 (
b1110 '
b0 +
b11 !
b11 %
b11 *
1"
#740000
0"
#745000
b10 (
b1 !
b1 %
b1 *
b1011 '
b10 +
1"
#750000
0"
#755000
b11 (
b1101 '
b11 +
b10 !
b10 %
b10 *
1"
#760000
0"
#765000
b1 (
b11 !
b11 %
b11 *
b1110 '
b0 +
1"
#770000
0"
#775000
b10 (
b1011 '
b10 +
b1 !
b1 %
b1 *
1"
#780000
0"
#785000
b11 (
b10 !
b10 %
b10 *
b1101 '
b11 +
1"
#790000
0"
#795000
b1 (
b1110 '
b0 +
b11 !
b11 %
b11 *
1"
#800000
0"
#805000
b10 (
b1 !
b1 %
b1 *
b1011 '
b10 +
1"
#810000
0"
#815000
b11 (
b1101 '
b11 +
b10 !
b10 %
b10 *
1"
#820000
0"
#825000
b1 (
b11 !
b11 %
b11 *
b1110 '
b0 +
1"
#830000
0"
#835000
b10 (
b1011 '
b10 +
b1 !
b1 %
b1 *
1"
#840000
0"
#845000
b11 (
b10 !
b10 %
b10 *
b1101 '
b11 +
1"
#850000
0"
#855000
b1 (
b1110 '
b0 +
b11 !
b11 %
b11 *
1"
#860000
0"
#865000
b10 (
b1 !
b1 %
b1 *
b1011 '
b10 +
1"
#870000
0"
#875000
b11 (
b1101 '
b11 +
b10 !
b10 %
b10 *
1"
#880000
0"
#885000
b1 (
b11 !
b11 %
b11 *
b1110 '
b0 +
1"
#890000
0"
#895000
b10 (
b1011 '
b10 +
b1 !
b1 %
b1 *
1"
#900000
0"
#905000
b11 (
b10 !
b10 %
b10 *
b1101 '
b11 +
1"
#910000
0"
#915000
b1 (
b1110 '
b0 +
b11 !
b11 %
b11 *
1"
#920000
0"
#925000
b10 (
b1 !
b1 %
b1 *
b1011 '
b10 +
1"
#930000
0"
#935000
b11 (
b1101 '
b11 +
b10 !
b10 %
b10 *
1"
#940000
0"
#945000
b1 (
b11 !
b11 %
b11 *
b1110 '
b0 +
1"
#950000
0"
#955000
b10 (
b1011 '
b10 +
b1 !
b1 %
b1 *
1"
#960000
0"
#965000
b11 (
b10 !
b10 %
b10 *
b1101 '
b11 +
1"
#970000
0"
#975000
b1 (
b1110 '
b0 +
b11 !
b11 %
b11 *
1"
#980000
0"
#985000
b10 (
b1 !
b1 %
b1 *
b1011 '
b10 +
1"
#990000
0"
#995000
b11 (
b1101 '
b11 +
b10 !
b10 %
b10 *
1"
