01_asf/asf.v
module asf(
	input wire wren,
	input wire [7:0] wrdata,
	input wire clkA,
	output wire isfull,

	input wire rden,
	input wire clkB,
	output wire [7:0] rddata,
	output wire isempty,

	input wire rstA,
	input wire rstB
);

	// pointers
	reg [2:0] n_wrptr;
	reg [2:0] n_rdptr;
    wire [2:0] g_wrptr;
	wire [2:0] g_rdptr;

	// array
	reg [7:0] mem [4];

	// 2FF synchronizer flops
	reg [2:0] ff1_f,ff2_f;
	reg [2:0] ff1_b,ff2_b;


    assign isfull = (g_wrptr[2] != ff2_b[2]) &&
                    (g_wrptr[1] != ff2_b[1]) &&
                    (g_wrptr[0] == ff2_b[0]);
    assign isempty = (ff2_f == g_rdptr);

    // n_wrptr
    always @(posedge clkA or negedge rstA) begin
        if (!rstA) n_wrptr <= 3'b0;
        else if (wren && !isfull) n_wrptr <= n_wrptr + 1;
    end

    // n_rdptr
    always @(posedge clkB or negedge rstB) begin
        if (!rstB) n_rdptr <= 3'b0;
        else if (rden && !isempty) n_rdptr <= n_rdptr + 1;
    end

    assign g_wrptr = (n_wrptr >> 1) ^ n_wrptr;
    assign g_rdptr = (n_rdptr >> 1) ^ n_rdptr;

    // 2FF sync
    always @(posedge clkB or negedge rstB) begin
        if (!rstB) begin
            ff1_f <= 3'b0;
            ff2_f <= 3'b0;
        end else begin
            ff1_f <= g_wrptr;
            ff2_f <= ff1_f;
        end
    end

    always @(posedge clkA or negedge rstA) begin
        if (!rstA) begin
            ff1_b <= 3'b0;
            ff2_b <= 3'b0;
        end else begin
            ff1_b <= g_rdptr;
            ff2_b <= ff1_b;
        end
    end

    always @(posedge clkA) begin
        if (wren && !isfull) mem[n_wrptr[1:0]] <= wrdata;
    end

    assign rddata = mem[n_rdptr[1:0]];

endmodule

01_asf/asf_tb.v
// THIS TESTBENCH WAS AI GENERATED

`timescale 1ns/1ps

module asf_tb;

    // =========================================================
    // DUT Signals
    // =========================================================
    reg        wren, rden;
    reg  [7:0] wrdata;
    reg        clkA, clkB;
    reg        rstA, rstB;
    wire [7:0] rddata;
    wire       isfull, isempty;

    // =========================================================
    // DUT Instantiation
    // =========================================================
    asf dut (
        .wren    (wren),
        .wrdata  (wrdata),
        .clkA    (clkA),
        .isfull  (isfull),
        .rden    (rden),
        .clkB    (clkB),
        .rddata  (rddata),
        .isempty (isempty),
        .rstA    (rstA),
        .rstB    (rstB)
    );

    // =========================================================
    // Clock Generation
    // =========================================================
    initial clkA = 0;
    initial clkB = 0;
    always #5  clkA = ~clkA;   // 100 MHz
    always #7  clkB = ~clkB;   //  ~71 MHz

    // =========================================================
    // Scoreboard
    // =========================================================
    reg [7:0] expected_q [0:15];
    integer   eq_head, eq_tail;

    // =========================================================
    // Waveform Dump
    // =========================================================
    initial begin
        $dumpfile("asf_tb.vcd");
        $dumpvars(0, asf_tb);
    end

    // =========================================================
    // Timeout Watchdog
    // =========================================================
    initial begin
        #50000;
        $display("[TIMEOUT] Simulation exceeded time limit");
        $finish;
    end

    // =========================================================
    // Test Sequence
    // =========================================================
    integer idx;

    initial begin
        // Init
        wren    = 0;
        rden    = 0;
        wrdata  = 0;
        rstA    = 0;
        rstB    = 0;
        eq_head = 0;
        eq_tail = 0;

        // -----------------------------------------------
        // TEST 1 — Reset
        // -----------------------------------------------
        $display("\n--- TEST 1: Reset ---");
        #20;
        rstA = 1;
        rstB = 1;
        #20;
        if (isempty !== 1'b1)
            $display("[FAIL] isempty should be 1 after reset, got %b", isempty);
        else
            $display("[PASS] isempty=1 after reset");

        if (isfull !== 1'b0)
            $display("[FAIL] isfull should be 0 after reset, got %b", isfull);
        else
            $display("[PASS] isfull=0 after reset");

        // Let synchronizers settle
        repeat(6) @(posedge clkA);

        // -----------------------------------------------
        // TEST 2 — Write until full
        // -----------------------------------------------
        $display("\n--- TEST 2: Fill FIFO ---");

        // Write entry 1
        @(posedge clkA); #1;
        wren = 1; wrdata = 8'h11;
        @(posedge clkA); #1;
        wren = 0;
        expected_q[eq_tail] = 8'h11; eq_tail = eq_tail + 1;

        // Write entry 2
        @(posedge clkA); #1;
        wren = 1; wrdata = 8'h22;
        @(posedge clkA); #1;
        wren = 0;
        expected_q[eq_tail] = 8'h22; eq_tail = eq_tail + 1;

        // Write entry 3
        @(posedge clkA); #1;
        wren = 1; wrdata = 8'h33;
        @(posedge clkA); #1;
        wren = 0;
        expected_q[eq_tail] = 8'h33; eq_tail = eq_tail + 1;

        // Write entry 4
        @(posedge clkA); #1;
        wren = 1; wrdata = 8'h44;
        @(posedge clkA); #1;
        wren = 0;
        expected_q[eq_tail] = 8'h44; eq_tail = eq_tail + 1;

        // Wait for isfull to propagate through synchronizer
        repeat(8) @(posedge clkA);
        if (isfull)
            $display("[PASS] FIFO correctly shows full");
        else
            $display("[FAIL] FIFO should be full");

        // -----------------------------------------------
        // TEST 3 — Write when full (should be ignored)
        // -----------------------------------------------
        $display("\n--- TEST 3: Write when Full ---");
        @(posedge clkA); #1;
        wren = 1; wrdata = 8'hFF;
        @(posedge clkA); #1;
        wren = 0;
        repeat(4) @(posedge clkA);
        if (isfull)
            $display("[PASS] Still full after overflow attempt");
        else
            $display("[FAIL] Should still be full");

        // -----------------------------------------------
        // TEST 4 — Read all data
        // -----------------------------------------------
        $display("\n--- TEST 4: Drain FIFO ---");
        repeat(4) @(posedge clkB);

        // Read entry 1
        @(posedge clkB); #1;
        // Sample FIRST, then increment
        if (rddata !== expected_q[eq_head])
            $display("[FAIL] Expected 0x%0h Got 0x%0h", expected_q[eq_head], rddata);
        else
            $display("[PASS] Read 0x%0h correct", rddata);
        eq_head = eq_head + 1;
        rden = 1;                  // increment AFTER sampling
        @(posedge clkB); #1;
        rden = 0;

        // Read entry 2
        @(posedge clkB); #1;
        rden = 1;
        @(posedge clkB); #1;
        if (rddata !== expected_q[eq_head])
            $display("[FAIL] Expected 0x%0h Got 0x%0h", expected_q[eq_head], rddata);
        else
            $display("[PASS] Read 0x%0h correct", rddata);
        eq_head = eq_head + 1;
        rden = 0;

        // Read entry 3
        @(posedge clkB); #1;
        rden = 1;
        @(posedge clkB); #1;
        if (rddata !== expected_q[eq_head])
            $display("[FAIL] Expected 0x%0h Got 0x%0h", expected_q[eq_head], rddata);
        else
            $display("[PASS] Read 0x%0h correct", rddata);
        eq_head = eq_head + 1;
        rden = 0;

        // Read entry 4
        @(posedge clkB); #1;
        rden = 1;
        @(posedge clkB); #1;
        if (rddata !== expected_q[eq_head])
            $display("[FAIL] Expected 0x%0h Got 0x%0h", expected_q[eq_head], rddata);
        else
            $display("[PASS] Read 0x%0h correct", rddata);
        eq_head = eq_head + 1;
        rden = 0;

        // Wait for isempty to propagate
        repeat(8) @(posedge clkB);
        if (isempty)
            $display("[PASS] FIFO correctly shows empty");
        else
            $display("[FAIL] FIFO should be empty");

        // -----------------------------------------------
        // TEST 5 — Read when empty (should be ignored)
        // -----------------------------------------------
        $display("\n--- TEST 5: Read when Empty ---");
        @(posedge clkB); #1;
        rden = 1;
        @(posedge clkB); #1;
        rden = 0;
        repeat(4) @(posedge clkB);
        if (isempty)
            $display("[PASS] Still empty after underflow attempt");
        else
            $display("[FAIL] Should still be empty");

        // -----------------------------------------------
        // Done
        // -----------------------------------------------
        $display("\n--- Simulation Complete ---");
        #100;
        $finish;
    end

endmodule

01_asf/asf_tb.vcd
$date
	Sat May 16 11:22:25 2026
$end
$version
	Icarus Verilog
$end
$timescale
	1ps
$end
$scope module asf_tb $end
$var wire 8 ! rddata [7:0] $end
$var wire 1 " isfull $end
$var wire 1 # isempty $end
$var reg 1 $ clkA $end
$var reg 1 % clkB $end
$var reg 1 & rden $end
$var reg 1 ' rstA $end
$var reg 1 ( rstB $end
$var reg 8 ) wrdata [7:0] $end
$var reg 1 * wren $end
$var integer 32 + eq_head [31:0] $end
$var integer 32 , eq_tail [31:0] $end
$scope module dut $end
$var wire 1 $ clkA $end
$var wire 1 % clkB $end
$var wire 3 - g_rdptr [2:0] $end
$var wire 3 . g_wrptr [2:0] $end
$var wire 1 " isfull $end
$var wire 8 / rddata [7:0] $end
$var wire 1 & rden $end
$var wire 1 ' rstA $end
$var wire 1 ( rstB $end
$var wire 8 0 wrdata [7:0] $end
$var wire 1 * wren $end
$var wire 1 # isempty $end
$var reg 3 1 ff1_b [2:0] $end
$var reg 3 2 ff1_f [2:0] $end
$var reg 3 3 ff2_b [2:0] $end
$var reg 3 4 ff2_f [2:0] $end
$var reg 3 5 n_rdptr [2:0] $end
$var reg 3 6 n_wrptr [2:0] $end
$upscope $end
$upscope $end
$enddefinitions $end
#0
$dumpvars
b0 6
b0 5
b0 4
b0 3
b0 2
b0 1
b0 0
bx /
b0 .
b0 -
b0 ,
b0 +
0*
b0 )
0(
0'
0&
0%
0$
1#
0"
bx !
$end
#5000
1$
#7000
1%
#10000
0$
#14000
0%
#15000
1$
#20000
0$
1(
1'
#21000
1%
#25000
1$
#28000
0%
#30000
0$
#35000
1$
1%
#40000
0$
#42000
0%
#45000
1$
#49000
1%
#50000
0$
#55000
1$
#56000
0%
#60000
0$
#63000
1%
#65000
1$
#70000
0$
0%
#75000
1$
#77000
1%
#80000
0$
#84000
0%
#85000
1$
#90000
0$
#91000
1%
#95000
1$
#98000
0%
#100000
0$
#105000
1$
1%
#106000
b10001 )
b10001 0
1*
#110000
0$
#112000
0%
#115000
b1 .
b10001 !
b10001 /
b1 6
1$
#116000
b1 ,
0*
#119000
b1 2
1%
#120000
0$
#125000
1$
#126000
b100010 )
b100010 0
1*
0%
#130000
0$
#133000
0#
b1 4
1%
#135000
b11 .
b10 6
1$
#136000
b10 ,
0*
#140000
0$
0%
#145000
1$
#146000
b110011 )
b110011 0
1*
#147000
b11 2
1%
#150000
0$
#154000
0%
#155000
b10 .
b11 6
1$
#156000
b11 ,
0*
#160000
0$
#161000
b11 4
b10 2
1%
#165000
1$
#166000
b1000100 )
b1000100 0
1*
#168000
0%
#170000
0$
#175000
1"
b110 .
b100 6
b10 4
1$
1%
#176000
b100 ,
0*
#180000
0$
#182000
0%
#185000
1$
#189000
b110 2
1%
#190000
0$
#195000
1$
#196000
0%
#200000
0$
#203000
b110 4
1%
#205000
1$
#210000
0$
0%
#215000
1$
#217000
1%
#220000
0$
#224000
0%
#225000
1$
#230000
0$
#231000
1%
#235000
1$
#238000
0%
#240000
0$
#245000
1$
1%
#250000
0$
#252000
0%
#255000
1$
#259000
1%
#260000
0$
#265000
1$
#266000
b11111111 )
b11111111 0
1*
0%
#270000
0$
#273000
1%
#275000
1$
#276000
0*
#280000
0$
0%
#285000
1$
#287000
1%
#290000
0$
#294000
0%
#295000
1$
#300000
0$
#301000
1%
#305000
1$
#308000
0%
#310000
0$
#315000
1$
1%
#320000
0$
#322000
0%
#325000
1$
#329000
1%
#330000
0$
#335000
1$
#336000
0%
#340000
0$
#343000
1%
#345000
1$
#350000
0$
0%
#355000
1$
#357000
1%
#360000
0$
#364000
0%
#365000
1$
#370000
0$
#371000
1%
#375000
1$
#378000
0%
#380000
0$
#385000
1$
1%
#386000
1&
b1 +
#390000
0$
#392000
0%
#395000
1$
#399000
b100010 !
b100010 /
b1 -
b1 5
1%
#400000
0&
0$
#405000
b1 1
1$
#406000
0%
#410000
0$
#413000
1%
#414000
1&
#415000
0"
b1 3
1$
#420000
0$
0%
#425000
1$
#427000
b110011 !
b110011 /
b11 -
b10 5
1%
#428000
0&
b10 +
#430000
0$
#434000
0%
#435000
b11 1
1$
#440000
0$
#441000
1%
#442000
1&
#445000
b11 3
1$
#448000
0%
#450000
0$
#455000
b1000100 !
b1000100 /
b10 -
b11 5
1$
1%
#456000
0&
b11 +
#460000
0$
#462000
0%
#465000
b10 1
1$
#469000
1%
#470000
1&
0$
#475000
b10 3
1$
#476000
0%
#480000
0$
#483000
1#
b10001 !
b10001 /
b110 -
b100 5
1%
#484000
0&
b100 +
#485000
b110 1
1$
#490000
0$
0%
#495000
b110 3
1$
#497000
1%
#500000
0$
#504000
0%
#505000
1$
#510000
0$
#511000
1%
#515000
1$
#518000
0%
#520000
0$
#525000
1$
1%
#530000
0$
#532000
0%
#535000
1$
#539000
1%
#540000
0$
#545000
1$
#546000
0%
#550000
0$
#553000
1%
#555000
1$
#560000
0$
0%
#565000
1$
#567000
1%
#570000
0$
#574000
0%
#575000
1$
#580000
0$
#581000
1%
#585000
1$
#588000
0%
#590000
0$
#595000
1$
1%
#600000
0$
#602000
0%
#605000
1$
#609000
1%
#610000
1&
0$
#615000
1$
#616000
0%
#620000
0$
#623000
1%
#624000
0&
